openrv/__init__.py
openrv/app.py
openrv/arduino.py
openrv/colors.py
openrv/contour.py
openrv/defines.py
openrv/image.py
openrv/utils.py
OpenRV-0.1.6.6.7.dist-info/LICENSE.txt
OpenRV-0.1.6.6.7.dist-info/METADATA
OpenRV-0.1.6.6.7.dist-info/WHEEL
OpenRV-0.1.6.6.7.dist-info/top_level.txt
OpenRV-0.1.6.6.7.dist-info/RECORD
