Metadata-Version: 2.1
Name: OpenRV
Version: 0.1.6.6.7
Summary: UNKNOWN
Home-page: https://github.com/OpenRoboVision/OpenRV
Author: kivicode
Author-email: kivicode@yandex.com
License: GNU GPLv3
Platform: UNKNOWN
Classifier: Programming Language :: Python :: 3.6
Classifier: License :: OSI Approved :: GNU General Public License v3 (GPLv3)
Requires-Dist: numpy (>=1.6)
Requires-Dist: opencv-python (<4.0)
Requires-Dist: scikit-image (>=0.16)
Requires-Dist: imutils (>=0.5.3)
Requires-Dist: scipy (>=1.3.1)
Requires-Dist: sklearn
